README.rst
setup.py
simplewebscraper.egg-info/PKG-INFO
simplewebscraper.egg-info/SOURCES.txt
simplewebscraper.egg-info/dependency_links.txt
simplewebscraper.egg-info/requires.txt
simplewebscraper.egg-info/top_level.txt
src/__init__.py
src/adapters.py
src/connection.py
src/convert_response.py
src/cookies.py
src/db_manager.py
src/enumerations.py
src/logger.py
src/proxy_aggregators.py
src/settings.py