Metadata-Version: 1.1
Name: simplewebscraper
Version: 1.43
Summary: Python library that makes web scraping very simple.
Home-page: https://github.com/alexanderward/simplewebscraper
Author: Alexander Ward
Author-email: alexander.ward1@gmail.com
License: lgpl
Platform: UNKNOWN
Classifier: Environment :: Web Environment
Classifier: Intended Audience :: Developers
Classifier: License :: OSI Approved :: GNU Library or Lesser General Public License (LGPL)
Classifier: Programming Language :: Python
Classifier: Topic :: Internet :: WWW/HTTP
Classifier: Operating System :: OS Independent
